{
  "README": {
    "designType": ["CheckBox", "RadioButton"],
    "multi": [true, false],
    "status": [true, false]
  },
  "courses": [
    {
      "capture": "",
      "description": "",
      "meta": {
        "institution": "",
        "specTitle": "",
        "specName": ""
      },
      "modules": [
        {
          "ytID": "",
          "capture": "",
          "questions": [
            {
              "designType": "CheckBox",
              "multi": true,
              "capture": "",
              "options": [
                { "label": "", "status": false },
                { "label": "", "status": false },
                { "label": "", "status": false },
                { "label": "", "status": false }
              ]
            },
            {
              "designType": "CheckBox",
              "multi": true,
              "capture": "",
              "options": [
                { "label": "", "status": false },
                { "label": "", "status": false },
                { "label": "", "status": false },
                { "label": "", "status": false }
              ]
            },
            {
              "designType": "CheckBox",
              "multi": true,
              "capture": "",
              "options": [
                { "label": "", "status": false },
                { "label": "", "status": false },
                { "label": "", "status": false },
                { "label": "", "status": false }
              ]
            },
            {
              "designType": "CheckBox",
              "multi": true,
              "capture": "",
              "options": [
                { "label": "", "status": false },
                { "label": "", "status": false },
                { "label": "", "status": false },
                { "label": "", "status": false }
              ]
            },
            {
              "designType": "CheckBox",
              "multi": true,
              "capture": "",
              "options": [
                { "label": "", "status": false },
                { "label": "", "status": false },
                { "label": "", "status": false },
                { "label": "", "status": false }
              ]
            }
          ]
        }
      ]
    }
  ]
}
